soccerapi/__init__.py
soccerapi/api/888sport.py
soccerapi/api/__init__.py
soccerapi/api/base.py
soccerapi/api/bet365.py
soccerapi/api/example.py
soccerapi/api/kambi.py
soccerapi/api/unibet.py
soccerapi/tests/test_api.py
soccerapi/tests/urls.py
soccerapi-0.7.1.dist-info/LICENSE
soccerapi-0.7.1.dist-info/WHEEL
soccerapi-0.7.1.dist-info/METADATA
soccerapi-0.7.1.dist-info/RECORD
