Metadata-Version: 2.1
Name: soccerapi
Version: 0.7.1
Summary: A simple python wrapper to get soccer odds
Home-page: https://github.com/S1M0N38/soccerapi
License: MIT
Author: S1M0N38
Author-email: bertolottosimone@gmail.com
Requires-Python: >=3.7,<4.0
Classifier: License :: OSI Approved :: MIT License
Classifier: Programming Language :: Python :: 3
Classifier: Programming Language :: Python :: 3.7
Classifier: Programming Language :: Python :: 3.8
Classifier: Programming Language :: Python :: 3.9
Requires-Dist: pyppeteer (>=0.2.5,<0.3.0)
Requires-Dist: requests (>=2.25.1,<3.0.0)
